honcho_core/__init__.py
honcho_core/_base_client.py
honcho_core/_client.py
honcho_core/_compat.py
honcho_core/_constants.py
honcho_core/_exceptions.py
honcho_core/_files.py
honcho_core/_models.py
honcho_core/_qs.py
honcho_core/_resource.py
honcho_core/_response.py
honcho_core/_streaming.py
honcho_core/_types.py
honcho_core/_version.py
honcho_core/pagination.py
honcho_core/py.typed
honcho_core/_utils/__init__.py
honcho_core/_utils/_compat.py
honcho_core/_utils/_datetime_parse.py
honcho_core/_utils/_logs.py
honcho_core/_utils/_proxy.py
honcho_core/_utils/_reflection.py
honcho_core/_utils/_resources_proxy.py
honcho_core/_utils/_streams.py
honcho_core/_utils/_sync.py
honcho_core/_utils/_transform.py
honcho_core/_utils/_typing.py
honcho_core/_utils/_utils.py
honcho_core/lib/.keep
honcho_core/resources/__init__.py
honcho_core/resources/workspaces/__init__.py
honcho_core/resources/workspaces/conclusions.py
honcho_core/resources/workspaces/queue.py
honcho_core/resources/workspaces/webhooks.py
honcho_core/resources/workspaces/workspaces.py
honcho_core/resources/workspaces/peers/__init__.py
honcho_core/resources/workspaces/peers/peers.py
honcho_core/resources/workspaces/peers/sessions.py
honcho_core/resources/workspaces/sessions/__init__.py
honcho_core/resources/workspaces/sessions/messages.py
honcho_core/resources/workspaces/sessions/peers.py
honcho_core/resources/workspaces/sessions/sessions.py
honcho_core/types/__init__.py
honcho_core/types/dream_configuration_param.py
honcho_core/types/peer_card_configuration_param.py
honcho_core/types/reasoning_configuration_param.py
honcho_core/types/summary_configuration_param.py
honcho_core/types/workspace.py
honcho_core/types/workspace_configuration_param.py
honcho_core/types/workspace_get_or_create_params.py
honcho_core/types/workspace_list_params.py
honcho_core/types/workspace_schedule_dream_params.py
honcho_core/types/workspace_search_params.py
honcho_core/types/workspace_search_response.py
honcho_core-1.11.0.dist-info/METADATA
honcho_core-1.11.0.dist-info/WHEEL
honcho_core-1.11.0.dist-info/licenses/LICENSE
honcho_core-1.11.0.dist-info/RECORD
